Metadata-Version: 2.1
Name: odoo10-addon-l10n-nl-tax-invoice-basis
Version: 10.0.1.0.1
Summary: Enable invoice basis on tax according to the Dutch law
Home-page: http://www.onestein.eu
Author: Onestein, Odoo Community Association (OCA)
Author-email: support@odoo-community.org
License: AGPL-3
Platform: UNKNOWN
Classifier: Programming Language :: Python
Classifier: Framework :: Odoo
Classifier: Framework :: Odoo :: 10.0
Classifier: License :: OSI Approved :: GNU Affero General Public License v3
Requires-Python: ~=2.7
Requires-Dist: odoo10-addon-account-tax-balance
Requires-Dist: odoo (<10.1dev,>=10.0)
